phd2client/__init__.py
phd2client/guider.py
phd2client/py.typed
phd2client-0.3.0.dist-info/licenses/LICENSE
phd2client-0.3.0.dist-info/WHEEL
phd2client-0.3.0.dist-info/METADATA
phd2client-0.3.0.dist-info/RECORD
