Metadata-Version: 2.4
Name: phd2client
Version: 0.3.0
Summary: PHD2 event server API client
Author: Andy Galasso
Author-email: Andy Galasso <andy.galasso@gmail.com>
License-Expression: MIT
License-File: LICENSE
Classifier: Development Status :: 4 - Beta
Classifier: Intended Audience :: Developers
Classifier: License :: OSI Approved :: MIT License
Classifier: Programming Language :: Python :: 3.13
Classifier: Topic :: Scientific/Engineering :: Astronomy
Classifier: Typing :: Typed
Requires-Python: >=3.13
Project-URL: Changelog, https://github.com/agalasso/phd2client/blob/master/python/CHANGELOG.md
Project-URL: Documentation, https://github.com/OpenPHDGuiding/phd2/wiki/EventMonitoring
Project-URL: Homepage, https://github.com/agalasso/phd2client/tree/master/python
Project-URL: Issues, https://github.com/agalasso/phd2client/issues
Project-URL: Repository, https://github.com/agalasso/phd2client
